MANIFEST.in
README.rst
setup.py
pony_wtf/__init__.py
pony_wtf/_compact.py
pony_wtf/converter.py
pony_wtf/orm.py
pony_wtf/requirements.txt
pony_wtf/utils.py
pony_wtf.egg-info/PKG-INFO
pony_wtf.egg-info/SOURCES.txt
pony_wtf.egg-info/dependency_links.txt
pony_wtf.egg-info/not-zip-safe
pony_wtf.egg-info/requires.txt
pony_wtf.egg-info/top_level.txt
pony_wtf/fields/__init__.py
pony_wtf/fields/json_field.py
pony_wtf/fields/list_fields.py
pony_wtf/fields/model_fields.py
pony_wtf/fields/select_fields.py
pony_wtf/fields/time_fields.py
pony_wtf/fields/widgets.py