Metadata-Version: 1.1
Name: pony-wtf
Version: 0.0.1.post7
Summary: Create WTF-Form from your pony database entity
Home-page: https://github.com/tabebqena/Pony-WTF
Author: Ahmad Yahia
Author-email: qenadev@gmail.com
License: MIT
Keywords: pony ponyorm wtf wtf-form
Platform: UNKNOWN
Classifier: License :: OSI Approved :: MIT License
